LICENSE.txt
MANIFEST.in
README.rst
ez_setup.py
setup.py
DynStatCov.egg-info/PKG-INFO
DynStatCov.egg-info/SOURCES.txt
DynStatCov.egg-info/dependency_links.txt
DynStatCov.egg-info/not-zip-safe
DynStatCov.egg-info/requires.txt
DynStatCov.egg-info/top_level.txt
dynstatcov/dynstatcov.c
dynstatcov/dynstatcov.pxd
dynstatcov/dynstatcov.pyx