Metadata-Version: 1.1
Name: DynStatCov
Version: 0.1.2
Summary: UNKNOWN
Home-page: https://github.com/loli/dynstatcov
Author: Oskar Maier
Author-email: oskar.maier@googlemail.com
License: LICENSE.txt
Keywords: dynamic statistical co-variance matrix update cython
Platform: UNKNOWN
Classifier: Development Status :: 5 - Production/Stable
Classifier: Environment :: Console
Classifier: Environment :: Other Environment
Classifier: Intended Audience :: Developers
Classifier: Intended Audience :: Science/Research
Classifier: License :: OSI Approved :: GNU General Public License (GPL)
Classifier: Operating System :: POSIX
Classifier: Operating System :: Unix
Classifier: Programming Language :: Python
Classifier: Programming Language :: Cython
Classifier: Programming Language :: C
Classifier: Topic :: Scientific/Engineering :: Mathematics
Classifier: Topic :: Software Development
